trellis_dag/__init__.py
trellis_dag/dag.py
trellis_dag/llm.py
trellis_dag/node.py
trellis_dag/tests/data.txt
trellis_dag/tests/test_dag.py
trellis_dag/tests/test_dag_execute.py
trellis_dag/tests/test_llm.py
trellis_dag/tests/test_node.py
trellis_dag/utils/analyzer.py
trellis_dag/utils/constants.py
trellis_dag/utils/generate.py
trellis_dag/utils/status.py
trellis_dag-0.1.6.dist-info/LICENSE
trellis_dag-0.1.6.dist-info/METADATA
trellis_dag-0.1.6.dist-info/WHEEL
trellis_dag-0.1.6.dist-info/RECORD
