Metadata-Version: 2.1
Name: trellis_dag
Version: 0.1.6
Summary: DAG-based LLM execution framework.
License: MIT
Author: Shivansh Rustagi
Author-email: me@shivan.sh
Requires-Python: >=3.9,<4.0
Classifier: License :: OSI Approved :: MIT License
Classifier: Programming Language :: Python :: 3
Classifier: Programming Language :: Python :: 3.9
Classifier: Programming Language :: Python :: 3.10
Classifier: Programming Language :: Python :: 3.11
Requires-Dist: aiohttp (>=3.8.5,<4.0.0)
Requires-Dist: openai (>=0.27.9,<0.28.0)
Requires-Dist: posthog (>=3.0.2,<4.0.0)
Requires-Dist: pytest (>=7.4.0,<8.0.0)
Requires-Dist: pytest-asyncio (>=0.21.1,<0.22.0)
Requires-Dist: pytest-mock (>=3.11.1,<4.0.0)
Requires-Dist: python-dotenv (>=1.0.0,<2.0.0)
Requires-Dist: voluptuous (>=0.13.1,<0.14.0)
